[
  {
    "name": "",
    "id": 1
  },
  {
    "name": "bottle",
    "id": 12
  },
  {
    "name": "clove",
    "id": 4
  },
  {
    "name": "gram",
    "id": 2
  },
  {
    "name": "kilogram",
    "id": 3
  },
  {
    "name": "litre",
    "id": 7
  },
  {
    "name": "millilitre",
    "id": 6
  },
  {
    "name": "packet",
    "id": 11
  },
  {
    "name": "pinch",
    "id": 10
  },
  {
    "name": "slice",
    "id": 13
  },
  {
    "name": "tablespoon",
    "id": 5
  },
  {
    "name": "teaspoon",
    "id": 8
  },
  {
    "name": "tin",
    "id": 9
  }
]
